quantum_QBD/__init__.py
quantum_QBD/dos.py
quantum_QBD/ldos.py
quantum_QBD/shroodinger__equation.py
quantum_QBD/tools.py
quantum_QBD-0.0.34.dist-info/LICENSE
quantum_QBD-0.0.34.dist-info/METADATA
quantum_QBD-0.0.34.dist-info/WHEEL
quantum_QBD-0.0.34.dist-info/top_level.txt
quantum_QBD-0.0.34.dist-info/RECORD
